Metadata-Version: 2.4
Name: python-ta
Version: 2.11.1
Summary: Code checking tool for teaching Python
Author-email: David Liu <david@cs.toronto.edu>
License: MIT
Project-URL: Homepage, https://github.com/pyta-uoft/pyta
Project-URL: Documentation, https://www.cs.toronto.edu/~david/pyta/
Project-URL: Repository, https://github.com/pyta-uoft/pyta.git
Project-URL: Changelog, https://github.com/pyta-uoft/pyta/blob/master/CHANGELOG.md
Requires-Python: >=3.9
License-File: LICENSE
Requires-Dist: aiohttp<3.13.0,>=3.11.18
Requires-Dist: astroid~=3.3.5
Requires-Dist: beautifulsoup4
Requires-Dist: black
Requires-Dist: click<9,>=8.0.1
Requires-Dist: colorama~=0.4.6
Requires-Dist: jinja2~=3.1.2
Requires-Dist: mypy~=1.13
Requires-Dist: pycodestyle~=2.11
Requires-Dist: pygments<2.20,>=2.14
Requires-Dist: pylint~=3.3.1
Requires-Dist: requests<2.33,>=2.28
Requires-Dist: six
Requires-Dist: tabulate~=0.9.0
Requires-Dist: toml~=0.10.2
Requires-Dist: typeguard<5,>=4.1.0
Requires-Dist: watchdog~=6.0.0
Requires-Dist: wrapt<2,>=1.15.0
Provides-Extra: dev
Requires-Dist: hypothesis; extra == "dev"
Requires-Dist: inflection; extra == "dev"
Requires-Dist: myst-parser; extra == "dev"
Requires-Dist: pre-commit; extra == "dev"
Requires-Dist: pytest; extra == "dev"
Requires-Dist: pytest-cov<6.3,>=4.0; extra == "dev"
Requires-Dist: pytest-mock; extra == "dev"
Requires-Dist: pytest-snapshot; extra == "dev"
Requires-Dist: websocket-client; extra == "dev"
Requires-Dist: sphinx; extra == "dev"
Requires-Dist: sphinx-rtd-theme; extra == "dev"
Provides-Extra: cfg
Requires-Dist: graphviz; extra == "cfg"
Provides-Extra: z3
Requires-Dist: z3-solver; extra == "z3"
Requires-Dist: importlib_resources; python_version < "3.9" and extra == "z3"
Dynamic: license-file
